ml4a/__init__.py
ml4a/audio.py
ml4a/image.py
ml4a/canvas/__init__.py
ml4a/canvas/canvas.py
ml4a/canvas/mask.py
ml4a/dataset/__init__.py
ml4a/dataset/dataset_utils.py
ml4a/dataset/generate_train_data.py
ml4a/dataset/processing.py
ml4a/dataset/scrape_wikiart.py
ml4a/models/__init__.py
ml4a/models/basnet.py
ml4a/models/cartoonization.py
ml4a/models/deepdream.py
ml4a/models/esrgan.py
ml4a/models/face_recognition.py
ml4a/models/flownet.py
ml4a/models/glow.py
ml4a/models/idinvert.py
ml4a/models/neural_style.py
ml4a/models/photosketch.py
ml4a/models/semantic_segmentation.py
ml4a/models/spade.py
ml4a/models/stylegan.py
ml4a/models/stylegan2.py
ml4a/models/tacotron2.py
ml4a/models/taming_transformers.py
ml4a/models/torch_dreams.py
ml4a/models/wav2lip.py
ml4a/models/submodules/__init__.py
ml4a/models/submodules/localimport.py
ml4a/models/submodules/BASNet/basnet_test.py
ml4a/models/submodules/BASNet/basnet_train.py
ml4a/models/submodules/BASNet/data_loader.py
ml4a/models/submodules/BASNet/model/BASNet.py
ml4a/models/submodules/BASNet/model/__init__.py
ml4a/models/submodules/BASNet/model/resnet_model.py
ml4a/models/submodules/BASNet/pytorch_iou/__init__.py
ml4a/models/submodules/BASNet/pytorch_ssim/__init__.py
ml4a/models/submodules/ESRGAN/RRDBNet_arch.py
ml4a/models/submodules/ESRGAN/net_interp.py
ml4a/models/submodules/ESRGAN/test.py
ml4a/models/submodules/ESRGAN/transer_RRDB_models.py
ml4a/models/submodules/FlowNetPytorch/flow_transforms.py
ml4a/models/submodules/FlowNetPytorch/main.py
ml4a/models/submodules/FlowNetPytorch/multiscaleloss.py
ml4a/models/submodules/FlowNetPytorch/run_inference.py
ml4a/models/submodules/FlowNetPytorch/util.py
ml4a/models/submodules/FlowNetPytorch/datasets/KITTI.py
ml4a/models/submodules/FlowNetPytorch/datasets/__init__.py
ml4a/models/submodules/FlowNetPytorch/datasets/flyingchairs.py
ml4a/models/submodules/FlowNetPytorch/datasets/listdataset.py
ml4a/models/submodules/FlowNetPytorch/datasets/mpisintel.py
ml4a-0.1.3.dist-info/LICENSE
ml4a-0.1.3.dist-info/METADATA
ml4a-0.1.3.dist-info/WHEEL
ml4a-0.1.3.dist-info/top_level.txt
ml4a-0.1.3.dist-info/RECORD
