Metadata-Version: 2.1
Name: ml4a
Version: 0.1.3
Summary: A toolkit for making art with machine learning, including an API for popular deep learning models, recipes for combining them, and a suite of educational examples
Home-page: http://github.com/ml4a/ml4a
Author: Gene Kogan
Author-email: gene@genekogan.com
License: MIT
Platform: UNKNOWN
Requires-Dist: bs4
Requires-Dist: dill
Requires-Dist: imutils
Requires-Dist: inflect
Requires-Dist: face-recognition
Requires-Dist: gdown
Requires-Dist: ipython
Requires-Dist: ipywidgets
Requires-Dist: librosa
Requires-Dist: lxml
Requires-Dist: matplotlib
Requires-Dist: moviepy
Requires-Dist: ninja
Requires-Dist: noise
Requires-Dist: numba
Requires-Dist: numpy
Requires-Dist: omegaconf (==2.0.0)
Requires-Dist: opencv-python
Requires-Dist: Pillow
Requires-Dist: pytorch-lightning (==1.0.8)
Requires-Dist: psutil
Requires-Dist: scikit-image
Requires-Dist: scikit-learn
Requires-Dist: tensorflow-gpu (==1.15.0)
Requires-Dist: torch
Requires-Dist: torchvision
Requires-Dist: tqdm
Requires-Dist: unidecode
Requires-Dist: yacs
